HISTORY.rst
LICENSE.txt
README.rst
setup.cfg
setup.py
ticketutil/__init__.py
ticketutil/bugzilla.py
ticketutil/jira.py
ticketutil/redmine.py
ticketutil/rt.py
ticketutil/servicenow.py
ticketutil/ticket.py
ticketutil.egg-info/PKG-INFO
ticketutil.egg-info/SOURCES.txt
ticketutil.egg-info/dependency_links.txt
ticketutil.egg-info/requires.txt
ticketutil.egg-info/top_level.txt