Metadata-Version: 2.1
Name: ticketutil
Version: 1.8.2
Summary: Python ticketing utility supporting JIRA, RT, Redmine, Bugzilla, and ServiceNow
Home-page: https://github.com/dmranck/ticketutil
Download-URL: https://github.com/dmranck/ticketutil/tarball/1.8.2
Author: Danny Ranck
Author-email: dmranck@gmail.com
Keywords: jira,bugzilla,rt,redmine,servicenow,ticket,rest
License-File: LICENSE.txt
